hubaxle/.gitignore
hubaxle/__init__.py
hubaxle/api/__init__.py
hubaxle/api/admin.py
hubaxle/api/basic_auth_middleware.py
hubaxle/api/emptyfile.txt
hubaxle/api/migrations/0001_initial.py
hubaxle/api/migrations/0002_alter_secret_name_alter_secret_value.py
hubaxle/api/migrations/0003_cameraconfig.py
hubaxle/api/migrations/__init__.py
hubaxle/api/models.py
hubaxle/api/serializers.py
hubaxle/api/test/test_config.yaml
hubaxle/api/test/tests.py
hubaxle/api/tests.py
hubaxle/api/urls.py
hubaxle/api/views.py
hubaxle/asgi.py
hubaxle/cfgstore/__init__.py
hubaxle/cfgstore/admin.py
hubaxle/cfgstore/apps.py
hubaxle/cfgstore/envkind.py
hubaxle/cfgstore/management/__init__.py
hubaxle/cfgstore/management/commands/__init__.py
hubaxle/cfgstore/management/commands/sync_config_entries.py
hubaxle/cfgstore/migrations/0001_new_table_configentry.py
hubaxle/cfgstore/migrations/__init__.py
hubaxle/cfgstore/models.py
hubaxle/cfgstore/serializers.py
hubaxle/cfgstore/tests.py
hubaxle/cfgstore/views.py
hubaxle/configtools.py
hubaxle/gldiscover.py
hubaxle/glhub_sdk/.gitignore
hubaxle/glhub_sdk/Makefile
hubaxle/glhub_sdk/README.md
hubaxle/glhub_sdk/api_plan.yaml
hubaxle/glhub_sdk/glhub_sdk/__init__.py
hubaxle/glhub_sdk/glhub_sdk/client.py
hubaxle/glhub_sdk/glhub_sdk/generated/.github/workflows/python.yml
hubaxle/glhub_sdk/glhub_sdk/generated/.gitignore
hubaxle/glhub_sdk/glhub_sdk/generated/.gitlab-ci.yml
hubaxle/glhub_sdk/glhub_sdk/generated/.openapi-generator/FILES
hubaxle/glhub_sdk/glhub_sdk/generated/.openapi-generator/VERSION
hubaxle/glhub_sdk/glhub_sdk/generated/.openapi-generator-ignore
hubaxle/glhub_sdk/glhub_sdk/generated/.travis.yml
hubaxle/glhub_sdk/glhub_sdk/generated/README.md
hubaxle/glhub_sdk/glhub_sdk/generated/docs/AppDataApi.md
hubaxle/glhub_sdk/glhub_sdk/generated/docs/CameraConfig.md
hubaxle/glhub_sdk/glhub_sdk/generated/docs/CamerasApi.md
hubaxle/glhub_sdk/glhub_sdk/generated/docs/ConfigEntry.md
hubaxle/glhub_sdk/glhub_sdk/generated/docs/ConfigEntryRequest.md
hubaxle-0.1.8.dist-info/METADATA
hubaxle-0.1.8.dist-info/WHEEL
hubaxle-0.1.8.dist-info/entry_points.txt
hubaxle-0.1.8.dist-info/RECORD
