Metadata-Version: 2.1
Name: hubaxle
Version: 0.1.8
Summary: Control interface for the GL Hub
License: MIT
Author: Groundlight
Author-email: info@groundlight.ai
Requires-Python: >=3.11,<4.0
Classifier: License :: OSI Approved :: MIT License
Classifier: Programming Language :: Python :: 3
Classifier: Programming Language :: Python :: 3.11
Classifier: Programming Language :: Python :: 3.12
Requires-Dist: django (>=5.0.10,<6.0.0)
Requires-Dist: djangorestframework (>=3.15.1,<4.0.0)
Requires-Dist: drf-spectacular (>=0.27.1,<0.28.0)
Requires-Dist: framegrab (>=0.6.2,<0.7.0)
Requires-Dist: groundlight (>=0.15.0,<0.16.0)
Requires-Dist: numpy (==1.26.4)
Requires-Dist: onvif-zeep (>=0.2.12,<0.3.0)
Requires-Dist: opencv-python (==4.9.0.80)
Requires-Dist: psutil (>=5.9.8,<6.0.0)
Requires-Dist: pytest (>=8.0.2,<9.0.0)
Requires-Dist: pytest-django (>=4.8.0,<5.0.0)
Requires-Dist: python-dotenv (>=1.0.1,<2.0.0)
Requires-Dist: pyyaml (>=6.0.1,<7.0.0)
Requires-Dist: requests (>=2.31.0,<3.0.0)
Requires-Dist: typer (>=0.9.0,<0.10.0)
Requires-Dist: wsdiscovery (>=2.0.0,<3.0.0)
